{
    "providers": {
        "awscloudformation": {
            "AuthRoleName": "circleapp-20190303201205-authRole",
            "UnauthRoleArn": "arn:aws:iam::397772462167:role/circleapp-20190303201205-unauthRole",
            "AuthRoleArn": "arn:aws:iam::397772462167:role/circleapp-20190303201205-authRole",
            "Region": "us-east-1",
            "DeploymentBucketName": "circleapp-20190303201205-deployment",
            "UnauthRoleName": "circleapp-20190303201205-unauthRole",
            "StackName": "circleapp-20190303201205",
            "StackId": "arn:aws:cloudformation:us-east-1:397772462167:stack/circleapp-20190303201205/6b431120-3e1a-11e9-af97-0ec11b444504"
        }
    },
    "auth": {
        "cognito86b844e0": {
            "service": "Cognito",
            "providerPlugin": "awscloudformation",
            "providerMetadata": {
                "s3TemplateURL": "https://s3.amazonaws.com/circleapp-20190303201205-deployment/amplify-cfn-templates/auth/cognito86b844e0-cloudformation-template.yml",
                "logicalId": "authcognito86b844e0"
            },
            "lastPushTimeStamp": "2019-03-04T01:59:39.864Z",
            "output": {
                "AppClientSecret": "m6t6vbpqsgjq137oeunltsqo23vh4le7mb9ni4ld7rhghckcudl",
                "UserPoolId": "us-east-1_kxdQvtrks",
                "AppClientIDWeb": "3t77p4ibe6u3oatrcbbc7djmt0",
                "AppClientID": "eiveof9qhts9k89tv78eq6qfm",
                "IdentityPoolId": "us-east-1:cbf1b35e-ad80-4e59-a5a0-c30a03234085",
                "IdentityPoolName": "cognito86b844e0_identitypool_86b844e0__master",
                "UserPoolName": "cognito86b844e0_userpool_86b844e0"
            },
            "lastPushDirHash": "A+oUqWQ0QAUxn/mYq0igPmiZ2T0="
        }
    },
    "hosting": {
        "S3AndCloudFront": {
            "service": "S3AndCloudFront",
            "providerPlugin": "awscloudformation",
            "providerMetadata": {
                "s3TemplateURL": "https://s3.amazonaws.com/circleapp-20190303201205-deployment/amplify-cfn-templates/hosting/template.json",
                "logicalId": "hostingS3AndCloudFront"
            },
            "lastPushTimeStamp": "2019-03-04T01:59:39.783Z",
            "output": {
                "S3BucketSecureURL": "https://circlepp-20190303205627-hostingbucket-master.s3.amazonaws.com",
                "WebsiteURL": "http://circlepp-20190303205627-hostingbucket-master.s3-website-us-east-1.amazonaws.com",
                "Region": "us-east-1",
                "HostingBucketName": "circlepp-20190303205627-hostingbucket-master"
            },
            "lastPushDirHash": "hQZ56LjZDnDSTkOp38MQVBPaLoM="
        }
    }
}